LICENSE
dlf_nova_play_my_own_music/__init__.py
dlf_nova_play_my_own_music/__main__.py
dlf_nova_play_my_own_music/cli.py
dlf_nova_play_my_own_music/constants.py
dlf_nova_play_my_own_music/create_dataset.py
dlf_nova_play_my_own_music/model_saves/weights.best.simple_cnn_more_features.hdf5
dlf_nova_play_my_own_music/prediction.py
dlf_nova_play_my_own_music/process_mp3_file.py
dlf_nova_play_my_own_music/saved_features_test.pickle
dlf_nova_play_my_own_music/saved_features_train.pickle
dlf_nova_play_my_own_music/simple_model.py
dlf_nova_play_my_own_music/simple_model_feature.py
dlf_nova_play_my_own_music/spotify_ctrl.py
dlf_nova_play_my_own_music/train_simple_model.py
dlf_nova_play_my_own_music-0.1.3.dist-info/entry_points.txt
dlf_nova_play_my_own_music-0.1.3.dist-info/LICENSE
dlf_nova_play_my_own_music-0.1.3.dist-info/WHEEL
dlf_nova_play_my_own_music-0.1.3.dist-info/METADATA
dlf_nova_play_my_own_music-0.1.3.dist-info/RECORD
