Metadata-Version: 2.1
Name: dlf-nova-play-my-own-music
Version: 0.1.3
Summary: Switches to Spotify if music is played on DLF Nova radio stream.
Home-page: https://github.com/AlxndrJhn/DLF-Nova-Play-My-Own-Music
License: MIT
Keywords: flake8,markdown,lint
Author: Alexander Jahn
Requires-Python: >=3.7,<4.0
Classifier: Development Status :: 4 - Beta
Classifier: Environment :: Console
Classifier: License :: OSI Approved :: MIT License
Classifier: Operating System :: OS Independent
Classifier: Programming Language :: Python :: 3
Classifier: Programming Language :: Python :: 3.7
Classifier: Programming Language :: Python :: 3.8
Classifier: Topic :: Internet
Classifier: Topic :: Multimedia :: Sound/Audio
Requires-Dist: Keras (>=2.3.1,<3.0.0)
Requires-Dist: click (>=7.1.2,<8.0.0)
Requires-Dist: numpy (>=1.18.4,<2.0.0)
Requires-Dist: pandas (>=1.0.3,<2.0.0)
Requires-Dist: pydub (>=0.24.0,<0.25.0)
Requires-Dist: python-vlc (>=3.0.9113,<4.0.0)
Requires-Dist: sklearn (>=0.0,<0.1)
Requires-Dist: spafe (>=0.1.2,<0.2.0)
Requires-Dist: spotipy (>=2.12.0,<3.0.0)
Project-URL: Repository, https://github.com/AlxndrJhn/DLF-Nova-Play-My-Own-Music
